{"cameraMode":{"drawMode":0,"name":"Shaded","section":"Shading Mode"},"sceneLighting":false,"audioPlay":false,"sceneViewState":{"m_AlwaysRefresh":false,"showFog":true,"showSkybox":false,"showFlares":true,"showImageEffects":true,"showParticleSystems":true,"showVisualEffectGraphs":true,"m_FxEnabled":true},"in2DMode":false,"pivot":{"x":4.983543395996094,"y":-5.517654895782471,"z":-38.23755645751953},"rotation":{"x":0.03224781155586243,"y":0.7471518516540527,"z":-0.03634731099009514,"w":0.6628761887550354},"size":43.605342864990237,"orthographic":false}